baskref/__init__.py
baskref/exceptions.py
baskref/settings.py
baskref/utils.py
baskref/data_collection/__init__.py
baskref/data_collection/baskref_data_scraper.py
baskref/data_collection/baskref_url_scraper.py
baskref/data_collection/html_scraper.py
baskref/data_saving/__init__.py
baskref/data_saving/file_saver.py
baskref-1.0.0.dist-info/LICENSE
baskref-1.0.0.dist-info/METADATA
baskref-1.0.0.dist-info/WHEEL
baskref-1.0.0.dist-info/entry_points.txt
baskref-1.0.0.dist-info/top_level.txt
baskref-1.0.0.dist-info/RECORD
