Metadata-Version: 2.1
Name: baskref
Version: 1.0.0
Summary: baskRef is a tool to scrape basketball Data from the web.
Author-email: Dominik Zulovec Sajovic <dominik.zsajovic@gmail.com>
License: MIT License
Project-URL: Homepage, https://github.com/orion512/basketball_scraper
Project-URL: Bug Tracker, https://github.com/orion512/basketball_scraper/issues
Project-URL: Project Board, https://github.com/users/orion512/projects/2/views/1
Keywords: basketball,web scraper,python
Classifier: Programming Language :: Python :: 3
Classifier: License :: OSI Approved :: MIT License
Classifier: Operating System :: OS Independent
Requires-Python: >=3.9
License-File: LICENSE
Requires-Dist: requests==2.28.1
Requires-Dist: beautifulsoup4==4.11.1
Requires-Dist: fake-useragent==1.1.1
